<?xml version="1.0" encoding="ISO-8859-1"?>
<tns:AutoDeclaracao
  xmlns:tns="http://www.tarea.com.br/InovarAuto/AutoDeclaracao"
  xmlns:xsi="http://www.w3.org/2001/XMLSchema-instance">
   <tns:retificadora>false</tns:retificadora>
   <tns:declarante>
      <tns:tipo_declarante>F</tns:tipo_declarante>
      <tns:razao_social>W.H.B DO BRASIL LTDA</tns:razao_social>
      <tns:cnpj>01111039000491</tns:cnpj>
      <tns:matriz>false</tns:matriz>
      <tns:operacao>
         <tns:natureza_operacao>V</tns:natureza_operacao>
         <tns:empresa>
            <tns:razao_social>MMC AUTOMOTORES DO BRASIL LTDA - GO</tns:razao_social>
            <tns:cnpj>54305743001170</tns:cnpj>
         </tns:empresa>
         <tns:mes_ref>08</tns:mes_ref>
         <tns:ano_ref>2017</tns:ano_ref>
         <tns:vl_total_notas>6801.82</tns:vl_total_notas>
         <tns:vl_parc_dedutivel>7.34</tns:vl_parc_dedutivel>
      </tns:operacao>
      <tns:operacao>
         <tns:natureza_operacao>V</tns:natureza_operacao>
         <tns:empresa>
            <tns:razao_social>HONDA AUTOMÓVEIS - Paulinia - SP</tns:razao_social>
            <tns:cnpj>01192333001366</tns:cnpj>
         </tns:empresa>
         <tns:mes_ref>08</tns:mes_ref>
         <tns:ano_ref>2017</tns:ano_ref>
         <tns:vl_total_notas>122115.50</tns:vl_total_notas>
         <tns:vl_parc_dedutivel>5856.70</tns:vl_parc_dedutivel>
      </tns:operacao>
      <tns:operacao>
         <tns:natureza_operacao>V</tns:natureza_operacao>
         <tns:empresa>
            <tns:razao_social>TOYOTA DO BRASIL LTDA</tns:razao_social>
            <tns:cnpj>59104760000191</tns:cnpj>
         </tns:empresa>
         <tns:mes_ref>08</tns:mes_ref>
         <tns:ano_ref>2017</tns:ano_ref>
         <tns:vl_total_notas>4863.61</tns:vl_total_notas>
         <tns:vl_parc_dedutivel>134.20</tns:vl_parc_dedutivel>
      </tns:operacao>
      <tns:operacao>
         <tns:natureza_operacao>V</tns:natureza_operacao>
         <tns:empresa>
            <tns:razao_social>TOYOTA DO BRASIL LTDA</tns:razao_social>
            <tns:cnpj>59104760000353</tns:cnpj>
         </tns:empresa>
         <tns:mes_ref>08</tns:mes_ref>
         <tns:ano_ref>2017</tns:ano_ref>
         <tns:vl_total_notas>47934.57</tns:vl_total_notas>
         <tns:vl_parc_dedutivel>0.96</tns:vl_parc_dedutivel>
      </tns:operacao>
      <tns:operacao>
         <tns:natureza_operacao>V</tns:natureza_operacao>
         <tns:empresa>
            <tns:razao_social>TOYOTA DO BRASIL LTDA</tns:razao_social>
            <tns:cnpj>59104760000604</tns:cnpj>
         </tns:empresa>
         <tns:mes_ref>08</tns:mes_ref>
         <tns:ano_ref>2017</tns:ano_ref>
         <tns:vl_total_notas>55405.41</tns:vl_total_notas>
         <tns:vl_parc_dedutivel>277.32</tns:vl_parc_dedutivel>
      </tns:operacao>

   </tns:declarante>
</tns:AutoDeclaracao>
